mlprovlab/__init__.py
mlprovlab/_version.py
mlprovlab/analyze.py
mlprovlab/handlers.py
mlprovlab/labextension/package.json
mlprovlab/labextension/static/158.8a7be9692cbb4db72a2c.js
mlprovlab/labextension/static/158.8a7be9692cbb4db72a2c.js.LICENSE.txt
mlprovlab/labextension/static/307.4011ecd37418fc4c414a.js
mlprovlab/labextension/static/534.e504e1e5b2471dd685f3.js
mlprovlab/labextension/static/548.0672aec541b994eddb8b.js
mlprovlab/labextension/static/58.cca9ffb2762ca79fd12d.js
mlprovlab/labextension/static/58.cca9ffb2762ca79fd12d.js.LICENSE.txt
mlprovlab/labextension/static/607.e98969ed5b40015345fa.js
mlprovlab/labextension/static/814.a58c44145b5777db1307.js
mlprovlab/labextension/static/817.ec382ae63396c2615752.js
mlprovlab/labextension/static/817.ec382ae63396c2615752.js.LICENSE.txt
mlprovlab/labextension/static/remoteEntry.d708b097832130df0f29.js
mlprovlab/labextension/static/style.js
mlprovlab/labextension/static/third-party-licenses.json
mlprovlab-0.1.0.data/data/etc/jupyter/jupyter_server_config.d/mlprovlab.json
mlprovlab-0.1.0.data/data/share/jupyter/labextensions/mlprovlab/install.json
mlprovlab-0.1.0.data/data/share/jupyter/labextensions/mlprovlab/package.json
mlprovlab-0.1.0.data/data/share/jupyter/labextensions/mlprovlab/static/158.8a7be9692cbb4db72a2c.js
mlprovlab-0.1.0.data/data/share/jupyter/labextensions/mlprovlab/static/158.8a7be9692cbb4db72a2c.js.LICENSE.txt
mlprovlab-0.1.0.data/data/share/jupyter/labextensions/mlprovlab/static/307.4011ecd37418fc4c414a.js
mlprovlab-0.1.0.data/data/share/jupyter/labextensions/mlprovlab/static/534.e504e1e5b2471dd685f3.js
mlprovlab-0.1.0.data/data/share/jupyter/labextensions/mlprovlab/static/548.0672aec541b994eddb8b.js
mlprovlab-0.1.0.data/data/share/jupyter/labextensions/mlprovlab/static/58.cca9ffb2762ca79fd12d.js
mlprovlab-0.1.0.data/data/share/jupyter/labextensions/mlprovlab/static/58.cca9ffb2762ca79fd12d.js.LICENSE.txt
mlprovlab-0.1.0.dist-info/LICENSE
mlprovlab-0.1.0.dist-info/METADATA
mlprovlab-0.1.0.dist-info/WHEEL
mlprovlab-0.1.0.dist-info/top_level.txt
mlprovlab-0.1.0.dist-info/RECORD
