Metadata-Version: 2.1
Name: mlprovlab
Version: 0.1.0
Summary: Provenance tracking and visualisation of machine learning scripts
Home-page: https://github.com/fusion-jena/MLProvLab
Author: Dominik Kerzel
Author-email: dominik.kerzel@uni-jena.de
License: MIT
Keywords: Jupyter,JupyterLab,JupyterLab3
Platform: Linux
Platform: Mac OS X
Platform: Windows
Classifier: License :: OSI Approved :: BSD License
Classifier: Programming Language :: Python
Classifier: Programming Language :: Python :: 3
Classifier: Programming Language :: Python :: 3.6
Classifier: Programming Language :: Python :: 3.7
Classifier: Programming Language :: Python :: 3.8
Classifier: Programming Language :: Python :: 3.9
Classifier: Framework :: Jupyter
Requires-Python: >=3.6
License-File: LICENSE
Requires-Dist: jupyterlab (~=3.0)
